{"blocks":[{"x":970,"y":360,"text":"cin >> choose;","width":380,"height":40,"type":"Ввод / вывод","isMenuBlock":false,"fontSize":14,"textHeight":14,"isBold":false,"isItalic":false,"textAlign":"center","labelsPosition":1},{"x":1050,"y":450,"text":"solveArrayTask();","width":380,"height":40,"type":"Подпрограмма","isMenuBlock":false,"fontSize":14,"textHeight":14,"isBold":false,"isItalic":false,"textAlign":"center","labelsPosition":1},{"x":1050,"y":530,"text":"solveMatrixTask();","width":380,"height":40,"type":"Подпрограмма","isMenuBlock":false,"fontSize":14,"textHeight":14,"isBold":false,"isItalic":false,"textAlign":"center","labelsPosition":1},{"x":1490,"y":450,"text":"break;","width":380,"height":40,"type":"Блок","isMenuBlock":false,"fontSize":14,"textHeight":14,"isBold":false,"isItalic":false,"textAlign":"center","labelsPosition":1},{"x":1490,"y":530,"text":"break;","width":380,"height":40,"type":"Блок","isMenuBlock":false,"fontSize":14,"textHeight":14,"isBold":false,"isItalic":false,"textAlign":"center","labelsPosition":1},{"x":620,"y":450,"text":"choose == 1","width":380,"height":40,"type":"Условие","isMenuBlock":false,"fontSize":14,"textHeight":14,"isBold":false,"isItalic":false,"textAlign":"center","labelsPosition":1},{"x":620,"y":530,"text":"choose == 2","width":380,"height":40,"type":"Условие","isMenuBlock":false,"fontSize":14,"textHeight":14,"isBold":false,"isItalic":false,"textAlign":"center","labelsPosition":1},{"x":620,"y":610,"text":"choose == 3","width":380,"height":40,"type":"Условие","isMenuBlock":false,"fontSize":14,"textHeight":14,"isBold":false,"isItalic":false,"textAlign":"center","labelsPosition":1},{"x":1490,"y":610,"text":"break;","width":380,"height":40,"type":"Блок","isMenuBlock":false,"fontSize":14,"textHeight":14,"isBold":false,"isItalic":false,"textAlign":"center","labelsPosition":1},{"x":970,"y":740,"text":"choose != 3","width":380,"height":40,"type":"Условие","isMenuBlock":false,"fontSize":14,"textHeight":14,"isBold":false,"isItalic":false,"textAlign":"center","labelsPosition":1},{"x":970,"y":850,"text":"конец","width":380,"height":30,"type":"Начало / конец","isMenuBlock":false,"fontSize":14,"textHeight":14,"isBold":false,"isItalic":false,"textAlign":"center","labelsPosition":1},{"x":970,"y":120,"text":"начало","width":380,"height":30,"type":"Начало / конец","isMenuBlock":false,"fontSize":14,"textHeight":14,"isBold":false,"isItalic":false,"textAlign":"center","labelsPosition":1},{"x":970,"y":190,"text":"int choose;","width":380,"height":40,"type":"Блок","isMenuBlock":false,"fontSize":14,"textHeight":14,"isBold":false,"isItalic":false,"textAlign":"center","labelsPosition":1},{"x":970,"y":280,"text":"\"Выберете какую задачу решить:\\n\";\n\"1. Задача с массивами\\n\";\n\"2. Задача с матрицами\\n\";\n\"3. Выход\\n\";","width":380,"height":60,"type":"Ввод / вывод","isMenuBlock":false,"fontSize":14,"textHeight":14,"isBold":false,"isItalic":false,"textAlign":"center","labelsPosition":1},{"x":2450,"y":110,"text":"начало\nsolveArrayTask()","width":380,"height":30,"type":"Начало / конец","isMenuBlock":false,"fontSize":14,"textHeight":14,"isBold":false,"isItalic":false,"textAlign":"center","labelsPosition":1},{"x":2450,"y":180,"text":"int n;","width":380,"height":40,"type":"Блок","isMenuBlock":false,"fontSize":14,"textHeight":14,"isBold":false,"isItalic":false,"textAlign":"center","labelsPosition":1},{"x":2450,"y":260,"text":"\"Введите размер массива: \"","width":380,"height":40,"type":"Ввод / вывод","isMenuBlock":false,"fontSize":14,"textHeight":14,"isBold":false,"isItalic":false,"textAlign":"center","labelsPosition":1},{"x":2450,"y":330,"text":"cin >> n;","width":380,"height":40,"type":"Ввод / вывод","isMenuBlock":false,"fontSize":14,"textHeight":14,"isBold":false,"isItalic":false,"textAlign":"center","labelsPosition":1},{"x":2450,"y":400,"text":"double* arr = new double[n];","width":380,"height":40,"type":"Блок","isMenuBlock":false,"fontSize":14,"textHeight":14,"isBold":false,"isItalic":false,"textAlign":"center","labelsPosition":1},{"x":2450,"y":470,"text":"\"Введите элементы массива:\\n\"","width":380,"height":40,"type":"Ввод / вывод","isMenuBlock":false,"fontSize":14,"textHeight":14,"isBold":false,"isItalic":false,"textAlign":"center","labelsPosition":1},{"x":2450,"y":540,"text":"int i = 0; i < n; ++i","width":380,"height":40,"type":"Цикл for","isMenuBlock":false,"fontSize":14,"textHeight":14,"isBold":false,"isItalic":false,"textAlign":"center","labelsPosition":1},{"x":2450,"y":610,"text":"cin >> arr[i];","width":380,"height":40,"type":"Ввод / вывод","isMenuBlock":false,"fontSize":14,"textHeight":14,"isBold":false,"isItalic":false,"textAlign":"center","labelsPosition":1},{"x":2450,"y":730,"text":"int minModIndex = 0;","width":380,"height":40,"type":"Блок","isMenuBlock":false,"fontSize":14,"textHeight":14,"isBold":false,"isItalic":false,"textAlign":"center","labelsPosition":1},{"x":2450,"y":800,"text":"int i = 1; i < n; ++i","width":380,"height":40,"type":"Цикл for","isMenuBlock":false,"fontSize":14,"textHeight":14,"isBold":false,"isItalic":false,"textAlign":"center","labelsPosition":1},{"x":2450,"y":880,"text":"abs(arr[i]) < abs(arr[minModIndex])","width":400,"height":40,"type":"Условие","isMenuBlock":false,"fontSize":14,"textHeight":14,"isBold":false,"isItalic":false,"textAlign":"center","labelsPosition":1},{"x":2450,"y":960,"text":"minModIndex = i","width":380,"height":40,"type":"Блок","isMenuBlock":false,"fontSize":14,"textHeight":14,"isBold":false,"isItalic":false,"textAlign":"center","labelsPosition":1},{"x":2450,"y":1090,"text":"int firstNegIndex = -1;","width":380,"height":40,"type":"Блок","isMenuBlock":false,"fontSize":14,"textHeight":14,"isBold":false,"isItalic":false,"textAlign":"center","labelsPosition":1},{"x":2450,"y":1160,"text":"int i = 0; i < n; ++i","width":380,"height":40,"type":"Цикл for","isMenuBlock":false,"fontSize":14,"textHeight":14,"isBold":false,"isItalic":false,"textAlign":"center","labelsPosition":1},{"x":2450,"y":1230,"text":"arr[i] < 0","width":380,"height":40,"type":"Условие","isMenuBlock":false,"fontSize":14,"textHeight":14,"isBold":false,"isItalic":false,"textAlign":"center","labelsPosition":1},{"x":2450,"y":1300,"text":"firstNegIndex = i;\r","width":380,"height":40,"type":"Блок","isMenuBlock":false,"fontSize":14,"textHeight":14,"isBold":false,"isItalic":false,"textAlign":"center","labelsPosition":1},{"x":2450,"y":1370,"text":"break;","width":380,"height":40,"type":"Блок","isMenuBlock":false,"fontSize":14,"textHeight":14,"isBold":false,"isItalic":false,"textAlign":"center","labelsPosition":1},{"x":2450,"y":1490,"text":"double sumAfterNeg = 0","width":380,"height":40,"type":"Блок","isMenuBlock":false,"fontSize":14,"textHeight":14,"isBold":false,"isItalic":false,"textAlign":"center","labelsPosition":1},{"x":2450,"y":1560,"text":"firstNegIndex != -1","width":400,"height":40,"type":"Условие","isMenuBlock":false,"fontSize":14,"textHeight":14,"isBold":false,"isItalic":false,"textAlign":"center","labelsPosition":1},{"x":2680,"y":1630,"text":"int i = firstNegIndex + 1; i < n; ++i","width":380,"height":40,"type":"Цикл for","isMenuBlock":false,"fontSize":14,"textHeight":14,"isBold":false,"isItalic":false,"textAlign":"center","labelsPosition":1},{"x":2680,"y":1700,"text":"sumAfterNeg += std::abs(arr[i]);","width":380,"height":40,"type":"Блок","isMenuBlock":false,"fontSize":14,"textHeight":14,"isBold":false,"isItalic":false,"textAlign":"center","labelsPosition":1},{"x":2460,"y":1980,"text":"   delete[] arr;","width":420,"height":40,"type":"Блок","isMenuBlock":false,"fontSize":14,"textHeight":14,"isBold":false,"isItalic":false,"textAlign":"center","labelsPosition":1},{"x":2460,"y":1910,"text":"\"Сумма модулей элементов после\n первого отрицательного: \" << sumAfterNeg","width":420,"height":40,"type":"Ввод / вывод","isMenuBlock":false,"fontSize":14,"textHeight":14,"isBold":false,"isItalic":false,"textAlign":"center","labelsPosition":1},{"x":2460,"y":1840,"text":"\"Номер минимального \nпо модулю элемента: \" << minModIndex","width":420,"height":40,"type":"Ввод / вывод","isMenuBlock":false,"fontSize":14,"textHeight":14,"isBold":false,"isItalic":false,"textAlign":"center","labelsPosition":1},{"x":3390,"y":100,"text":"начало\nsolveMatrixTask()","width":380,"height":30,"type":"Начало / конец","isMenuBlock":false,"fontSize":14,"textHeight":14,"isBold":false,"isItalic":false,"textAlign":"center","labelsPosition":1},{"x":3390,"y":170,"text":"int size;","width":380,"height":40,"type":"Блок","isMenuBlock":false,"fontSize":14,"textHeight":14,"isBold":false,"isItalic":false,"textAlign":"center","labelsPosition":1},{"x":3390,"y":240,"text":" \"Введите размер матрицы: \"","width":380,"height":40,"type":"Ввод / вывод","isMenuBlock":false,"fontSize":14,"textHeight":14,"isBold":false,"isItalic":false,"textAlign":"center","labelsPosition":1},{"x":3390,"y":310,"text":"cin >> size;","width":380,"height":40,"type":"Ввод / вывод","isMenuBlock":false,"fontSize":14,"textHeight":14,"isBold":false,"isItalic":false,"textAlign":"center","labelsPosition":1},{"x":3390,"y":380,"text":"int* matrix = new int[size * size];","width":380,"height":40,"type":"Блок","isMenuBlock":false,"fontSize":14,"textHeight":14,"isBold":false,"isItalic":false,"textAlign":"center","labelsPosition":1},{"x":3390,"y":450,"text":"int i = 0; i < size; ++i","width":380,"height":40,"type":"Цикл for","isMenuBlock":false,"fontSize":14,"textHeight":14,"isBold":false,"isItalic":false,"textAlign":"center","labelsPosition":1},{"x":3390,"y":520,"text":"int j = 0; j < size; ++j","width":380,"height":40,"type":"Цикл for","isMenuBlock":false,"fontSize":14,"textHeight":14,"isBold":false,"isItalic":false,"textAlign":"center","labelsPosition":1},{"x":3390,"y":590,"text":"\"Введите элемент [\" << i << \"][\" << j << \"]: \"","width":380,"height":40,"type":"Ввод / вывод","isMenuBlock":false,"fontSize":14,"textHeight":14,"isBold":false,"isItalic":false,"textAlign":"center","labelsPosition":1},{"x":3390,"y":660,"text":"matrix[i * size + j]","width":380,"height":40,"type":"Ввод / вывод","isMenuBlock":false,"fontSize":14,"textHeight":14,"isBold":false,"isItalic":false,"textAlign":"center","labelsPosition":1},{"x":3390,"y":820,"text":"int product = 1;","width":380,"height":40,"type":"Блок","isMenuBlock":false,"fontSize":14,"textHeight":14,"isBold":false,"isItalic":false,"textAlign":"center","labelsPosition":1},{"x":3390,"y":890,"text":"int i = 0; i < size; ++i","width":380,"height":40,"type":"Цикл for","isMenuBlock":false,"fontSize":14,"textHeight":14,"isBold":false,"isItalic":false,"textAlign":"center","labelsPosition":1},{"x":3390,"y":960,"text":" bool hasNeg = false;","width":380,"height":40,"type":"Блок","isMenuBlock":false,"fontSize":14,"textHeight":14,"isBold":false,"isItalic":false,"textAlign":"center","labelsPosition":1},{"x":3390,"y":1030,"text":"int j = 0; j < size; ++j","width":380,"height":40,"type":"Цикл for","isMenuBlock":false,"fontSize":14,"textHeight":14,"isBold":false,"isItalic":false,"textAlign":"center","labelsPosition":1},{"x":3390,"y":1100,"text":"matrix[i * size + j] < 0","width":380,"height":40,"type":"Условие","isMenuBlock":false,"fontSize":14,"textHeight":14,"isBold":false,"isItalic":false,"textAlign":"center","labelsPosition":1},{"x":3390,"y":1180,"text":"hasNeg = true;","width":380,"height":40,"type":"Блок","isMenuBlock":false,"fontSize":14,"textHeight":14,"isBold":false,"isItalic":false,"textAlign":"center","labelsPosition":1},{"x":3390,"y":1250,"text":" break;","width":380,"height":40,"type":"Блок","isMenuBlock":false,"fontSize":14,"textHeight":14,"isBold":false,"isItalic":false,"textAlign":"center","labelsPosition":1},{"x":3390,"y":1380,"text":"!hasNeg","width":380,"height":40,"type":"Условие","isMenuBlock":false,"fontSize":14,"textHeight":14,"isBold":false,"isItalic":false,"textAlign":"center","labelsPosition":1},{"x":3450,"y":1450,"text":"int j = 0; j < size; ++j","width":380,"height":40,"type":"Цикл for","isMenuBlock":false,"fontSize":14,"textHeight":14,"isBold":false,"isItalic":false,"textAlign":"center","labelsPosition":1},{"x":3450,"y":1520,"text":"product *= matrix[i * size + j];","width":380,"height":40,"type":"Блок","isMenuBlock":false,"fontSize":14,"textHeight":14,"isBold":false,"isItalic":false,"textAlign":"center","labelsPosition":1},{"x":3390,"y":1660,"text":"int maxDiagonalSum = 0;","width":380,"height":40,"type":"Блок","isMenuBlock":false,"fontSize":14,"textHeight":14,"isBold":false,"isItalic":false,"textAlign":"center","labelsPosition":1},{"x":3390,"y":1730,"text":"int i = 0; i < size - 1; ++i","width":380,"height":40,"type":"Цикл for","isMenuBlock":false,"fontSize":14,"textHeight":14,"isBold":false,"isItalic":false,"textAlign":"center","labelsPosition":1},{"x":3390,"y":1800,"text":"int diagonalSum = 0;","width":380,"height":40,"type":"Блок","isMenuBlock":false,"fontSize":14,"textHeight":14,"isBold":false,"isItalic":false,"textAlign":"center","labelsPosition":1},{"x":3390,"y":1870,"text":"int j = 0; j < size - i; ++j","width":380,"height":40,"type":"Цикл for","isMenuBlock":false,"fontSize":14,"textHeight":14,"isBold":false,"isItalic":false,"textAlign":"center","labelsPosition":1},{"x":3390,"y":1940,"text":"diagonalSum += matrix[(i + j) * size + j];","width":380,"height":40,"type":"Блок","isMenuBlock":false,"fontSize":14,"textHeight":14,"isBold":false,"isItalic":false,"textAlign":"center","labelsPosition":1},{"x":3390,"y":2070,"text":"int j = 0; j < size - i; ++j","width":380,"height":40,"type":"Цикл for","isMenuBlock":false,"fontSize":14,"textHeight":14,"isBold":false,"isItalic":false,"textAlign":"center","labelsPosition":1},{"x":3390,"y":2140,"text":"diagonalSum += matrix[j * size + (i + j)]","width":380,"height":40,"type":"Блок","isMenuBlock":false,"fontSize":14,"textHeight":14,"isBold":false,"isItalic":false,"textAlign":"center","labelsPosition":1},{"x":3390,"y":2270,"text":"maxDiagonalSum = max(maxDiagonalSum, diagonalSum);","width":380,"height":40,"type":"Блок","isMenuBlock":false,"fontSize":14,"textHeight":14,"isBold":false,"isItalic":false,"textAlign":"center","labelsPosition":1},{"x":3390,"y":2380,"text":"\"Произведение элементов в строках \nбез отрицательных элементов: \" << product","width":380,"height":40,"type":"Ввод / вывод","isMenuBlock":false,"fontSize":14,"textHeight":14,"isBold":false,"isItalic":false,"textAlign":"center","labelsPosition":1},{"x":3390,"y":2450,"text":"\"Максимум среди сумм элементов диагоналей, \nпараллельных главной диагонали: \" << maxDiagonalSum","width":380,"height":40,"type":"Ввод / вывод","isMenuBlock":false,"fontSize":14,"textHeight":14,"isBold":false,"isItalic":false,"textAlign":"center","labelsPosition":1},{"x":3390,"y":2520,"text":"delete[] matrix;","width":380,"height":40,"type":"Блок","isMenuBlock":false,"fontSize":14,"textHeight":14,"isBold":false,"isItalic":false,"textAlign":"center","labelsPosition":1},{"x":2460,"y":2060,"text":"конец \nsolveArrayTask()","width":380,"height":30,"type":"Начало / конец","isMenuBlock":false,"fontSize":14,"textHeight":14,"isBold":false,"isItalic":false,"textAlign":"center","labelsPosition":1},{"x":3390,"y":2590,"text":"конец \nsolveMatrixTask();","width":380,"height":30,"type":"Начало / конец","isMenuBlock":false,"fontSize":14,"textHeight":14,"isBold":false,"isItalic":false,"textAlign":"center","labelsPosition":1}],"arrows":[{"startIndex":11,"endIndex":12,"startConnectorIndex":2,"endConnectorIndex":0,"nodes":[{"x":970,"y":135},{"x":970,"y":150},{"x":970,"y":170}],"counts":[1,1,1]},{"startIndex":12,"endIndex":13,"startConnectorIndex":2,"endConnectorIndex":0,"nodes":[{"x":970,"y":210},{"x":970,"y":230},{"x":970,"y":250}],"counts":[1,1,1]},{"startIndex":13,"endIndex":0,"startConnectorIndex":2,"endConnectorIndex":0,"nodes":[{"x":970,"y":310},{"x":970,"y":320},{"x":970,"y":340}],"counts":[1,1,1]},{"startIndex":0,"endIndex":5,"startConnectorIndex":2,"endConnectorIndex":0,"nodes":[{"x":970,"y":380},{"x":970,"y":410},{"x":620,"y":410},{"x":620,"y":430}],"counts":[1,1,1,1]},{"startIndex":6,"endIndex":7,"startConnectorIndex":3,"endConnectorIndex":0,"nodes":[{"x":430,"y":530},{"x":410,"y":530},{"x":410,"y":570},{"x":620,"y":570},{"x":620,"y":590}],"counts":[1,1,1,1,1]},{"startIndex":5,"endIndex":6,"startConnectorIndex":3,"endConnectorIndex":0,"nodes":[{"x":430,"y":450},{"x":410,"y":450},{"x":410,"y":490},{"x":620,"y":490},{"x":620,"y":510}],"counts":[1,1,1,1,1]},{"startIndex":5,"endIndex":1,"startConnectorIndex":1,"endConnectorIndex":3,"nodes":[{"x":810,"y":450},{"x":840,"y":450},{"x":860,"y":450}],"counts":[1,1,1]},{"startIndex":6,"endIndex":2,"startConnectorIndex":1,"endConnectorIndex":3,"nodes":[{"x":810,"y":530},{"x":840,"y":530},{"x":860,"y":530}],"counts":[1,1,1]},{"startIndex":1,"endIndex":3,"startConnectorIndex":1,"endConnectorIndex":3,"nodes":[{"x":1240,"y":450},{"x":1280,"y":450},{"x":1300,"y":450}],"counts":[1,1,1]},{"startIndex":2,"endIndex":4,"startConnectorIndex":1,"endConnectorIndex":3,"nodes":[{"x":1240,"y":530},{"x":1280,"y":530},{"x":1300,"y":530}],"counts":[1,1,1]},{"startIndex":7,"endIndex":8,"startConnectorIndex":1,"endConnectorIndex":3,"nodes":[{"x":810,"y":610},{"x":1280,"y":610},{"x":1300,"y":610}],"counts":[1,1,1]},{"startIndex":3,"endIndex":9,"startConnectorIndex":1,"endConnectorIndex":0,"nodes":[{"x":1680,"y":450},{"x":1700,"y":450},{"x":1700,"y":670},{"x":970,"y":670},{"x":970,"y":720}],"counts":[1,1,1,1,1]},{"startIndex":4,"endIndex":9,"startConnectorIndex":1,"endConnectorIndex":0,"nodes":[{"x":1680,"y":530},{"x":1700,"y":530},{"x":1700,"y":670},{"x":970,"y":670},{"x":970,"y":720}],"counts":[1,1,1,1,1]},{"startIndex":8,"endIndex":9,"startConnectorIndex":1,"endConnectorIndex":0,"nodes":[{"x":1680,"y":610},{"x":1700,"y":610},{"x":1700,"y":670},{"x":970,"y":670},{"x":970,"y":720}],"counts":[1,1,1,1,1]},{"startIndex":9,"endIndex":10,"startConnectorIndex":3,"endConnectorIndex":0,"nodes":[{"x":780,"y":740},{"x":760,"y":740},{"x":760,"y":820},{"x":970,"y":820},{"x":970,"y":835}],"counts":[1,1,1,1,1]},{"startIndex":9,"endIndex":13,"startConnectorIndex":1,"endConnectorIndex":0,"nodes":[{"x":1160,"y":740},{"x":1750,"y":740},{"x":1750,"y":230},{"x":970,"y":230},{"x":970,"y":250}],"counts":[1,1,1,1,1]},{"startIndex":14,"endIndex":15,"startConnectorIndex":2,"endConnectorIndex":0,"nodes":[{"x":2450,"y":125},{"x":2450,"y":140},{"x":2450,"y":160}],"counts":[1,1,1]},{"startIndex":15,"endIndex":16,"startConnectorIndex":2,"endConnectorIndex":0,"nodes":[{"x":2450,"y":200},{"x":2450,"y":220},{"x":2450,"y":240}],"counts":[1,1,1]},{"startIndex":16,"endIndex":17,"startConnectorIndex":2,"endConnectorIndex":0,"nodes":[{"x":2450,"y":280},{"x":2450,"y":290},{"x":2450,"y":310}],"counts":[1,1,1]},{"startIndex":17,"endIndex":18,"startConnectorIndex":2,"endConnectorIndex":0,"nodes":[{"x":2450,"y":350},{"x":2450,"y":360},{"x":2450,"y":380}],"counts":[1,1,1]},{"startIndex":18,"endIndex":19,"startConnectorIndex":2,"endConnectorIndex":0,"nodes":[{"x":2450,"y":420},{"x":2450,"y":430},{"x":2450,"y":450}],"counts":[1,1,1]},{"startIndex":19,"endIndex":20,"startConnectorIndex":2,"endConnectorIndex":0,"nodes":[{"x":2450,"y":490},{"x":2450,"y":500},{"x":2450,"y":520}],"counts":[1,1,1]},{"startIndex":20,"endIndex":21,"startConnectorIndex":2,"endConnectorIndex":0,"nodes":[{"x":2450,"y":560},{"x":2450,"y":570},{"x":2450,"y":590}],"counts":[1,1,1]},{"startIndex":21,"endIndex":20,"startConnectorIndex":2,"endConnectorIndex":3,"nodes":[{"x":2450,"y":630},{"x":2450,"y":660},{"x":2220,"y":660},{"x":2220,"y":540},{"x":2240,"y":540},{"x":2260,"y":540}],"counts":[1,1,1,1,1,1]},{"startIndex":20,"endIndex":22,"startConnectorIndex":1,"endConnectorIndex":0,"nodes":[{"x":2640,"y":540},{"x":2670,"y":540},{"x":2670,"y":690},{"x":2450,"y":690},{"x":2450,"y":710}],"counts":[1,1,1,1,1]},{"startIndex":22,"endIndex":23,"startConnectorIndex":2,"endConnectorIndex":0,"nodes":[{"x":2450,"y":750},{"x":2450,"y":760},{"x":2450,"y":780}],"counts":[1,1,1]},{"startIndex":23,"endIndex":24,"startConnectorIndex":2,"endConnectorIndex":0,"nodes":[{"x":2450,"y":820},{"x":2450,"y":840},{"x":2450,"y":860}],"counts":[1,1,1]},{"startIndex":24,"endIndex":25,"startConnectorIndex":1,"endConnectorIndex":0,"nodes":[{"x":2650,"y":880},{"x":2670,"y":880},{"x":2670,"y":920},{"x":2450,"y":920},{"x":2450,"y":940}],"counts":[1,1,1,1,1]},{"startIndex":24,"endIndex":23,"startConnectorIndex":3,"endConnectorIndex":3,"nodes":[{"x":2250,"y":880},{"x":2190,"y":880},{"x":2190,"y":800},{"x":2240,"y":800},{"x":2260,"y":800}],"counts":[1,1,1,1,1]},{"startIndex":25,"endIndex":23,"startConnectorIndex":2,"endConnectorIndex":3,"nodes":[{"x":2450,"y":980},{"x":2450,"y":1010},{"x":2190,"y":1010},{"x":2190,"y":800},{"x":2240,"y":800},{"x":2260,"y":800}],"counts":[1,1,1,1,1,1]},{"startIndex":23,"endIndex":26,"startConnectorIndex":1,"endConnectorIndex":0,"nodes":[{"x":2640,"y":800},{"x":2680,"y":800},{"x":2680,"y":1050},{"x":2450,"y":1050},{"x":2450,"y":1070}],"counts":[1,1,1,1,1]},{"startIndex":26,"endIndex":27,"startConnectorIndex":2,"endConnectorIndex":0,"nodes":[{"x":2450,"y":1110},{"x":2450,"y":1120},{"x":2450,"y":1140}],"counts":[1,1,1]},{"startIndex":27,"endIndex":28,"startConnectorIndex":2,"endConnectorIndex":0,"nodes":[{"x":2450,"y":1180},{"x":2450,"y":1190},{"x":2450,"y":1210}],"counts":[1,1,1]},{"startIndex":28,"endIndex":29,"startConnectorIndex":1,"endConnectorIndex":0,"nodes":[{"x":2640,"y":1230},{"x":2660,"y":1230},{"x":2660,"y":1260},{"x":2450,"y":1260},{"x":2450,"y":1280}],"counts":[1,1,1,1,1]},{"startIndex":29,"endIndex":30,"startConnectorIndex":2,"endConnectorIndex":0,"nodes":[{"x":2450,"y":1320},{"x":2450,"y":1330},{"x":2450,"y":1350}],"counts":[1,1,1]},{"startIndex":28,"endIndex":27,"startConnectorIndex":3,"endConnectorIndex":3,"nodes":[{"x":2260,"y":1230},{"x":2210,"y":1230},{"x":2210,"y":1160},{"x":2260,"y":1160}],"counts":[1,1,1,1]},{"startIndex":30,"endIndex":27,"startConnectorIndex":2,"endConnectorIndex":3,"nodes":[{"x":2450,"y":1390},{"x":2450,"y":1420},{"x":2210,"y":1420},{"x":2210,"y":1160},{"x":2240,"y":1160},{"x":2260,"y":1160}],"counts":[1,1,1,1,1,1]},{"startIndex":27,"endIndex":31,"startConnectorIndex":1,"endConnectorIndex":0,"nodes":[{"x":2640,"y":1160},{"x":2680,"y":1160},{"x":2680,"y":1450},{"x":2450,"y":1450},{"x":2450,"y":1470}],"counts":[1,1,1,1,1]},{"startIndex":31,"endIndex":32,"startConnectorIndex":2,"endConnectorIndex":0,"nodes":[{"x":2450,"y":1510},{"x":2450,"y":1520},{"x":2450,"y":1540}],"counts":[1,1,1]},{"startIndex":32,"endIndex":33,"startConnectorIndex":1,"endConnectorIndex":0,"nodes":[{"x":2650,"y":1560},{"x":2680,"y":1560},{"x":2680,"y":1590},{"x":2680,"y":1610}],"counts":[1,1,1,1]},{"startIndex":33,"endIndex":34,"startConnectorIndex":2,"endConnectorIndex":0,"nodes":[{"x":2680,"y":1650},{"x":2680,"y":1660},{"x":2680,"y":1680}],"counts":[1,1,1]},{"startIndex":34,"endIndex":33,"startConnectorIndex":2,"endConnectorIndex":3,"nodes":[{"x":2680,"y":1720},{"x":2680,"y":1770},{"x":2460,"y":1770},{"x":2460,"y":1630},{"x":2470,"y":1630},{"x":2490,"y":1630}],"counts":[1,1,1,1,1,1]},{"startIndex":37,"endIndex":36,"startConnectorIndex":2,"endConnectorIndex":0,"nodes":[{"x":2460,"y":1860},{"x":2460,"y":1870},{"x":2460,"y":1890}],"counts":[1,1,1]},{"startIndex":32,"endIndex":37,"startConnectorIndex":3,"endConnectorIndex":0,"nodes":[{"x":2250,"y":1560},{"x":2230,"y":1560},{"x":2230,"y":1800},{"x":2460,"y":1800},{"x":2460,"y":1820}],"counts":[1,1,1,1,1]},{"startIndex":33,"endIndex":37,"startConnectorIndex":1,"endConnectorIndex":0,"nodes":[{"x":2870,"y":1630},{"x":2890,"y":1630},{"x":2890,"y":1800},{"x":2460,"y":1800},{"x":2460,"y":1820}],"counts":[1,1,1,1,1]},{"startIndex":36,"endIndex":35,"startConnectorIndex":2,"endConnectorIndex":0,"nodes":[{"x":2460,"y":1930},{"x":2460,"y":1940},{"x":2460,"y":1960}],"counts":[1,1,1]},{"startIndex":35,"endIndex":68,"startConnectorIndex":2,"endConnectorIndex":0,"nodes":[{"x":2460,"y":2000},{"x":2460,"y":2030},{"x":2460,"y":2045}],"counts":[1,1,1]},{"startIndex":38,"endIndex":39,"startConnectorIndex":2,"endConnectorIndex":0,"nodes":[{"x":3390,"y":115},{"x":3390,"y":130},{"x":3390,"y":150}],"counts":[1,1,1]},{"startIndex":39,"endIndex":40,"startConnectorIndex":2,"endConnectorIndex":0,"nodes":[{"x":3390,"y":190},{"x":3390,"y":200},{"x":3390,"y":220}],"counts":[1,1,1]},{"startIndex":40,"endIndex":41,"startConnectorIndex":2,"endConnectorIndex":0,"nodes":[{"x":3390,"y":260},{"x":3390,"y":270},{"x":3390,"y":290}],"counts":[1,1,1]},{"startIndex":41,"endIndex":42,"startConnectorIndex":2,"endConnectorIndex":0,"nodes":[{"x":3390,"y":330},{"x":3390,"y":340},{"x":3390,"y":360}],"counts":[1,1,1]},{"startIndex":42,"endIndex":43,"startConnectorIndex":2,"endConnectorIndex":0,"nodes":[{"x":3390,"y":400},{"x":3390,"y":410},{"x":3390,"y":430}],"counts":[1,1,1]},{"startIndex":43,"endIndex":44,"startConnectorIndex":2,"endConnectorIndex":0,"nodes":[{"x":3390,"y":470},{"x":3390,"y":480},{"x":3390,"y":500}],"counts":[1,1,1]},{"startIndex":44,"endIndex":45,"startConnectorIndex":2,"endConnectorIndex":0,"nodes":[{"x":3390,"y":540},{"x":3390,"y":550},{"x":3390,"y":570}],"counts":[1,1,1]},{"startIndex":45,"endIndex":46,"startConnectorIndex":2,"endConnectorIndex":0,"nodes":[{"x":3390,"y":610},{"x":3390,"y":620},{"x":3390,"y":640}],"counts":[1,1,1]},{"startIndex":46,"endIndex":44,"startConnectorIndex":2,"endConnectorIndex":3,"nodes":[{"x":3390,"y":680},{"x":3390,"y":710},{"x":3170,"y":710},{"x":3170,"y":520},{"x":3180,"y":520},{"x":3200,"y":520}],"counts":[1,1,1,1,1,1]},{"startIndex":44,"endIndex":43,"startConnectorIndex":1,"endConnectorIndex":3,"nodes":[{"x":3580,"y":520},{"x":3610,"y":520},{"x":3610,"y":740},{"x":3140,"y":740},{"x":3140,"y":450},{"x":3180,"y":450},{"x":3200,"y":450}],"counts":[1,1,1,1,1,1,1]},{"startIndex":43,"endIndex":47,"startConnectorIndex":1,"endConnectorIndex":0,"nodes":[{"x":3580,"y":450},{"x":3680,"y":450},{"x":3680,"y":770},{"x":3390,"y":770},{"x":3390,"y":800}],"counts":[1,1,1,1,1]},{"startIndex":47,"endIndex":48,"startConnectorIndex":2,"endConnectorIndex":0,"nodes":[{"x":3390,"y":840},{"x":3390,"y":850},{"x":3390,"y":870}],"counts":[1,1,1]},{"startIndex":48,"endIndex":49,"startConnectorIndex":2,"endConnectorIndex":0,"nodes":[{"x":3390,"y":910},{"x":3390,"y":920},{"x":3390,"y":940}],"counts":[1,1,1]},{"startIndex":49,"endIndex":50,"startConnectorIndex":2,"endConnectorIndex":0,"nodes":[{"x":3390,"y":980},{"x":3390,"y":990},{"x":3390,"y":1010}],"counts":[1,1,1]},{"startIndex":50,"endIndex":51,"startConnectorIndex":2,"endConnectorIndex":0,"nodes":[{"x":3390,"y":1050},{"x":3390,"y":1060},{"x":3390,"y":1080}],"counts":[1,1,1]},{"startIndex":52,"endIndex":53,"startConnectorIndex":2,"endConnectorIndex":0,"nodes":[{"x":3390,"y":1200},{"x":3390,"y":1210},{"x":3390,"y":1230}],"counts":[1,1,1]},{"startIndex":51,"endIndex":52,"startConnectorIndex":1,"endConnectorIndex":0,"nodes":[{"x":3580,"y":1100},{"x":3600,"y":1100},{"x":3600,"y":1140},{"x":3390,"y":1140},{"x":3390,"y":1160}],"counts":[1,1,1,1,1]},{"startIndex":51,"endIndex":50,"startConnectorIndex":3,"endConnectorIndex":3,"nodes":[{"x":3200,"y":1100},{"x":3170,"y":1100},{"x":3170,"y":1030},{"x":3200,"y":1030}],"counts":[1,1,1,1]},{"startIndex":53,"endIndex":50,"startConnectorIndex":2,"endConnectorIndex":3,"nodes":[{"x":3390,"y":1270},{"x":3390,"y":1300},{"x":3170,"y":1300},{"x":3170,"y":1030},{"x":3180,"y":1030},{"x":3200,"y":1030}],"counts":[1,1,1,1,1,1]},{"startIndex":54,"endIndex":55,"startConnectorIndex":1,"endConnectorIndex":0,"nodes":[{"x":3580,"y":1380},{"x":3600,"y":1380},{"x":3600,"y":1410},{"x":3450,"y":1410},{"x":3450,"y":1430}],"counts":[1,1,1,1,1]},{"startIndex":55,"endIndex":56,"startConnectorIndex":2,"endConnectorIndex":0,"nodes":[{"x":3450,"y":1470},{"x":3450,"y":1480},{"x":3450,"y":1500}],"counts":[1,1,1]},{"startIndex":56,"endIndex":55,"startConnectorIndex":2,"endConnectorIndex":3,"nodes":[{"x":3450,"y":1540},{"x":3450,"y":1560},{"x":3240,"y":1560},{"x":3240,"y":1450},{"x":3260,"y":1450}],"counts":[1,1,1,1,1]},{"startIndex":50,"endIndex":54,"startConnectorIndex":1,"endConnectorIndex":0,"nodes":[{"x":3580,"y":1030},{"x":3610,"y":1030},{"x":3610,"y":1340},{"x":3390,"y":1340},{"x":3390,"y":1360}],"counts":[1,1,1,1,1]},{"startIndex":54,"endIndex":50,"startConnectorIndex":3,"endConnectorIndex":3,"nodes":[{"x":3200,"y":1380},{"x":3110,"y":1380},{"x":3110,"y":1030},{"x":3200,"y":1030}],"counts":[1,1,1,1]},{"startIndex":55,"endIndex":48,"startConnectorIndex":1,"endConnectorIndex":3,"nodes":[{"x":3640,"y":1450},{"x":3660,"y":1450},{"x":3660,"y":1590},{"x":3080,"y":1590},{"x":3080,"y":890},{"x":3180,"y":890},{"x":3200,"y":890}],"counts":[1,1,1,1,1,1,1]},{"startIndex":48,"endIndex":57,"startConnectorIndex":1,"endConnectorIndex":0,"nodes":[{"x":3580,"y":890},{"x":3690,"y":890},{"x":3690,"y":1630},{"x":3390,"y":1630},{"x":3390,"y":1640}],"counts":[1,1,1,1,1]},{"startIndex":57,"endIndex":58,"startConnectorIndex":2,"endConnectorIndex":0,"nodes":[{"x":3390,"y":1680},{"x":3390,"y":1690},{"x":3390,"y":1710}],"counts":[1,1,1]},{"startIndex":58,"endIndex":59,"startConnectorIndex":2,"endConnectorIndex":0,"nodes":[{"x":3390,"y":1750},{"x":3390,"y":1760},{"x":3390,"y":1780}],"counts":[1,1,1]},{"startIndex":59,"endIndex":60,"startConnectorIndex":2,"endConnectorIndex":0,"nodes":[{"x":3390,"y":1820},{"x":3390,"y":1830},{"x":3390,"y":1850}],"counts":[1,1,1]},{"startIndex":60,"endIndex":61,"startConnectorIndex":2,"endConnectorIndex":0,"nodes":[{"x":3390,"y":1890},{"x":3390,"y":1900},{"x":3390,"y":1920}],"counts":[1,1,1]},{"startIndex":61,"endIndex":60,"startConnectorIndex":2,"endConnectorIndex":3,"nodes":[{"x":3390,"y":1960},{"x":3390,"y":2010},{"x":3170,"y":2010},{"x":3170,"y":1870},{"x":3200,"y":1870}],"counts":[1,1,1,1,1]},{"startIndex":60,"endIndex":62,"startConnectorIndex":1,"endConnectorIndex":0,"nodes":[{"x":3580,"y":1870},{"x":3600,"y":1870},{"x":3600,"y":2030},{"x":3390,"y":2030},{"x":3390,"y":2050}],"counts":[1,1,1,1,1]},{"startIndex":62,"endIndex":63,"startConnectorIndex":2,"endConnectorIndex":0,"nodes":[{"x":3390,"y":2090},{"x":3390,"y":2100},{"x":3390,"y":2120}],"counts":[1,1,1]},{"startIndex":63,"endIndex":62,"startConnectorIndex":2,"endConnectorIndex":3,"nodes":[{"x":3390,"y":2160},{"x":3390,"y":2200},{"x":3140,"y":2200},{"x":3140,"y":2070},{"x":3180,"y":2070},{"x":3200,"y":2070}],"counts":[1,1,1,1,1,1]},{"startIndex":62,"endIndex":64,"startConnectorIndex":1,"endConnectorIndex":0,"nodes":[{"x":3580,"y":2070},{"x":3600,"y":2070},{"x":3600,"y":2230},{"x":3390,"y":2230},{"x":3390,"y":2250}],"counts":[1,1,1,1,1]},{"startIndex":64,"endIndex":58,"startConnectorIndex":2,"endConnectorIndex":3,"nodes":[{"x":3390,"y":2290},{"x":3390,"y":2310},{"x":3130,"y":2310},{"x":3130,"y":1730},{"x":3180,"y":1730},{"x":3200,"y":1730}],"counts":[1,1,1,1,1,1]},{"startIndex":65,"endIndex":66,"startConnectorIndex":2,"endConnectorIndex":0,"nodes":[{"x":3390,"y":2400},{"x":3390,"y":2410},{"x":3390,"y":2430}],"counts":[1,1,1]},{"startIndex":58,"endIndex":65,"startConnectorIndex":1,"endConnectorIndex":0,"nodes":[{"x":3580,"y":1730},{"x":3690,"y":1730},{"x":3690,"y":2340},{"x":3390,"y":2340},{"x":3390,"y":2360}],"counts":[1,1,1,1,1]},{"startIndex":66,"endIndex":67,"startConnectorIndex":2,"endConnectorIndex":0,"nodes":[{"x":3390,"y":2470},{"x":3390,"y":2480},{"x":3390,"y":2500}],"counts":[1,1,1]},{"startIndex":67,"endIndex":69,"startConnectorIndex":2,"endConnectorIndex":0,"nodes":[{"x":3390,"y":2540},{"x":3390,"y":2560},{"x":3390,"y":2575}],"counts":[1,1,1]}],"x0":-2158,"y0":-1771}